lmchain/__init__.py
lmchain/config.py
lmchain/hello.py
lmchain/tool_register.py
lmchain/agents/__init__.py
lmchain/agents/characterAgent.py
lmchain/agents/character_agent.py
lmchain/agents/llmAgent.py
lmchain/agents/llmMultiActionAgent.py
lmchain/agents/llmMultiAgent.py
lmchain/agents/simple_multi_agent.py
lmchain/agents/simple_multi_agent_experiment.py
lmchain/agents/strict_json_agent_wrapper.py
lmchain/agents/toolAgent.py
lmchain/callbacks/__init__.py
lmchain/callbacks/base.py
lmchain/callbacks/manager.py
lmchain/callbacks/stdout.py
lmchain/chains/__init__.py
lmchain/chains/base.py
lmchain/chains/cmd.py
lmchain/chains/conversationalRetrievalChain.py
lmchain/chains/llm.py
lmchain/chains/mathChain.py
lmchain/chains/question_answering.py
lmchain/chains/subQuestChain.py
lmchain/chains/toolchain.py
lmchain/chains/urlRequestChain.py
lmchain/embeddings/__init__.py
lmchain/embeddings/embeddings.py
lmchain/index/__init__.py
lmchain/index/indexChain.py
lmchain/llms/__init__.py
lmchain/llms/base.py
lmchain/load/__init__.py
lmchain/load/serializable.py
lmchain/load/textsplitter.py
lmchain/memory/__init__.py
lmchain/memory/chat_memory.py
lmchain/memory/messageHistory.py
lmchain/memory/utils.py
lmchain/model/__init__.py
lmchain/model/language_model.py
lmchain/prompts/Tst.py
lmchain/prompts/__init__.py
lmchain/prompts/base.py
lmchain/prompts/chat.py
lmchain/prompts/example_selectors.py
lmchain/prompts/few_shot_templates.py
lmchain/prompts/loading.py
lmchain/prompts/prompt.py
lmchain/prompts/prompt_template.py
lmchain/prompts/prompt_templates.py
lmchain/prompts/templates.py
lmchain/prompts/tool_templates.py
lmchain/schema/__init__.py
lmchain/schema/agent.py
lmchain/schema/document.py
lmchain/schema/language_model.py
lmchain/schema/memory.py
lmchain/schema/messages.py
lmchain/schema/output.py
lmchain/schema/output_parser.py
lmchain/schema/prompt.py
lmchain/schema/prompt_template.py
lmchain/schema/runnable.py
lmchain/schema/runnable_utils.py
lmchain/schema/schema.py
LMchain-0.2.26.dist-info/LICENSE
LMchain-0.2.26.dist-info/METADATA
LMchain-0.2.26.dist-info/WHEEL
LMchain-0.2.26.dist-info/top_level.txt
LMchain-0.2.26.dist-info/RECORD
