Metadata-Version: 2.1
Name: LMchain
Version: 0.2.26
Summary: A large chinese freelanguage chain tools,you can get free API from:open.bigmodel.cn
Home-page: https://github.com/virgo777/lmchain/
Author: xiaohuaWang
Author-email: xiaohuaWang <5847713@qq.com>
Project-URL: Homepage, https://github.com/virgo777/lmchain
Project-URL: Bug Tracker, https://github.com/virgo777/lmchain/issues
Classifier: Programming Language :: Python :: 3
Classifier: License :: OSI Approved :: MIT License
Classifier: Operating System :: OS Independent
Requires-Python: >=3
License-File: LICENSE
Requires-Dist: uvicorn
Requires-Dist: fastapi
Requires-Dist: zhipuai
Requires-Dist: gradio
Requires-Dist: requests
Requires-Dist: numpy
